Metadata-Version: 1.0
Name: pyscan
Version: 1.0.0
Summary: Python scanner using the Nmap library
Home-page: UNKNOWN
Author: BrainDisassembly
Author-email: braindisassm@gmail.com
License: GPL v3
Platform: UNKNOWN
